LICENSE
README.md
setup.cfg
setup.py
RestOC/CLI.py
RestOC/Conf.py
RestOC/DateTimeHelper.py
RestOC/DictHelper.py
RestOC/EMail.py
RestOC/Environment.py
RestOC/Errors.py
RestOC/Image.py
RestOC/JSON.py
RestOC/REST.py
RestOC/Record_Base.py
RestOC/Record_MySQL.py
RestOC/Record_ReDB.py
RestOC/Resize.py
RestOC/SMTP.py
RestOC/Services.py
RestOC/Session.py
RestOC/StrHelper.py
RestOC/Templates.py
RestOC/__init__.py
rest_oc.egg-info/PKG-INFO
rest_oc.egg-info/SOURCES.txt
rest_oc.egg-info/dependency_links.txt
rest_oc.egg-info/requires.txt
rest_oc.egg-info/top_level.txt
rest_oc.egg-info/zip-safe