Metadata-Version: 2.1
Name: rest-oc
Version: 1.2.8
Summary: Rest-OC is a library of python 3 modules for rapidly setting up REST microservices.
Home-page: https://ouroboroscoding.com/rest-oc/
Author: Chris Nasr - Ouroboros Coding Inc.
Author-email: chris@ouroboroscoding.com
License: MIT
Project-URL: Documentation, https://ouroboroscoding.com/rest-oc/
Project-URL: Source, https://github.com/ouroboroscoding/rest-oc-python
Project-URL: Tracker, https://github.com/ouroboroscoding/rest-oc-python/issues
Keywords: rest,microservices
Requires-Python: >=3.10
License-File: LICENSE
